jsonism/__init__.py
jsonism/checker.py
jsonism/types.py
tests/__init__.py
tests/test_basic.py
tests/test_check.py
tests/test_types.py
tests/test_values.py
jsonism-1.1.2.dist-info/LICENSE.md
jsonism-1.1.2.dist-info/METADATA
jsonism-1.1.2.dist-info/WHEEL
jsonism-1.1.2.dist-info/top_level.txt
jsonism-1.1.2.dist-info/RECORD
