Metadata-Version: 2.1
Name: jsonism
Version: 1.1.2
Summary: A simple JSON schema checker
Home-page: https://github.com/bmcollier/jsonism
Author: Ben Collier
Author-email: bencollier@fastmail.com
License: 3-Clause BSD
Platform: UNKNOWN
License-File: LICENSE.md
